Workbook
Name Slicer_Category: #N/A
Name Slicer_Region: #N/A
Name Slicer_Sales_Channel: #N/A
Name Slicer_Status: #N/A

Sheet Sheet2
A3: Row Labels | B3: Sum of Net Sales
A4: Smartphone | B4: 133950
A5: Laptop | B5: 95680
A6: Projector | B6: 85560
A7: Camera | B7: 78120
A8: Tablet | B8: 77440
A9: Refrigerator | B9: 72380
A10: Printer | B10: 66600
A11: Washing Machine | B11: 57960
A12: Monitor | B12: 41216
A13: Smartwatch | B13: 40320
A14: Grand Total | B14: 749226
A18: Row Labels | B18: Sum of Net Sales
A19: north | B19: 4845
A20: East | B20: 392316
A21: North | B21: 499870.9
A22: South | B22: 189429.4
A23: West | B23: 507802.5
A24: Grand Total | B24: 1594263.8
A28: Row Labels | B28: Sum of Net Sales
A29: Cancelled | B29: 12960
A30: Completed | B30: 1455631.8
A31: Pending | B31: 81752
A32: Refunded | B32: 43920
A33: Grand Total | B33: 1594263.8
A37: Row Labels | B37: Sum of Net Sales
A38: Jan | B38: 529893.4
A39: Feb | B39: 243171.5
A40: Mar | B40: 463243.2
A41: Apr | B41: 248214.9
A42: May | B42: 109740.8
A43: Grand Total | B43: 1594263.8
E45: kpi cards

Sheet dashboard

Sheet Sheet1
A1: Transaction_ID | B1: Date | C1: Region | D1: Sales_Channel | E1: Customer_Name | F1: Category | G1: Product | H1: Quantity | I1: Unit_Price_INR | J1: Discount_Rate | K1: Payment_Method | L1: Status | M1: Sales_Rep_ID | N1: Grow Sales | O1: Discount Amount | P1: Net Sales | Q1: Transaction Month | R1: Transaction Flag | S1: Netsale Classification | T1: Quantity&Discount Flag | U1: Cash OR UPI | V1: Price per unit(IFERROR) | W1: cleaned customer name | X1: Standardized Regions | Y1: Extract year&month | Z1: MID-numeric from Trans.ID | AA1: combine region&category
A2: TXN1015 | B2: 46045 | C2: West | D2: Wholesale | E2: Ocean Traders | F2: Electronics | G2: Smartphone | H2: 5 | I2: 28500 | J2: 0.06 | K2: Bank Transfer | L2: Completed | M2: EMP02 | N2: =Table1[[#This Row],[Quantity]]*Table1[[#This Row],[Unit_Price_INR]] -> 142500 | O2: =Table1[[#This Row],[Grow Sales]]*Table1[[#This Row],[Discount_Rate]] -> 8550 | P2: =Table1[[#This Row],[Grow Sales]]-Table1[[#This Row],[Discount Amount]] -> 133950 | Q2: =TEXT(Table1[[#This Row],[Date]],"MMM-ddd-yyyy") -> Jan-Fri-2026 | R2: =IF(OR(Table1[[#This Row],[Status]]="Pending",Table1[[#This Row],[Status]]="Refunded"),"Review","OK") -> OK | S2: =IF(Table1[[#This Row],[Net Sales]]>=25000,"High",IF(Table1[[#This Row],[Net Sales]]>=10000,"Medium","Low")) -> High | T2: =IF(AND(Table1[[#This Row],[Quantity]]>=5,Table1[[#This Row],[Discount_Rate]]>=10%),"Review","OK") -> OK | U2: =IF(OR(Table1[[#This Row],[Payment_Method]]="Cash",Table1[[#This Row],[Payment_Method]]="UPI"),"YES","NO") -> NO | V2: =IFERROR(Table1[[#This Row],[Net Sales]]/Table1[[#This Row],[Quantity]],"check data") -> 26790 | W2: =PROPER(TRIM(Table1[[#This Row],[Customer_Name]])) -> Ocean Traders | X2: =UPPER(TRIM(Table1[[#This Row],[Region]])) -> WEST | Y2: =TEXT(Table1[[#This Row],[Date]],"MMMM-yyyy") -> January-2026 | Z2: =MID(Table1[[#This Row],[Transaction_ID]],4,6) -> 1015 | AA2: =Table1[[#This Row],[Region]]&"-"&Table1[[#This Row],[Category]] -> West-Electronics
A3: TXN1001 | B3: 46025 | C3: North | D3: Retail | E3: Asha Stores | F3: Electronics | G3: Laptop | H3: 2 | I3: 52000 | J3: 0.08 | K3: UPI | L3: Completed | M3: EMP01 | N3: =Table1[[#This Row],[Quantity]]*Table1[[#This Row],[Unit_Price_INR]] -> 104000 | O3: =Table1[[#This Row],[Grow Sales]]*Table1[[#This Row],[Discount_Rate]] -> 8320 | P3: =Table1[[#This Row],[Grow Sales]]-Table1[[#This Row],[Discount Amount]] -> 95680 | Q3: =TEXT(Table1[[#This Row],[Date]],"MMM-ddd-yyyy") -> Jan-Sat-2026 | R3: =IF(OR(Table1[[#This Row],[Status]]="Pending",Table1[[#This Row],[Status]]="Refunded"),"Review","OK") -> OK | S3: =IF(Table1[[#This Row],[Net Sales]]>=25000,"High",IF(Table1[[#This Row],[Net Sales]]>=10000,"Medium","Low")) -> High | T3: =IF(AND(Table1[[#This Row],[Quantity]]>=5,Table1[[#This Row],[Discount_Rate]]>=10%),"Review","OK") -> OK | U3: =IF(OR(Table1[[#This Row],[Payment_Method]]="Cash",Table1[[#This Row],[Payment_Method]]="UPI"),"YES","NO") -> YES | V3: =IFERROR(Table1[[#This Row],[Net Sales]]/Table1[[#This Row],[Quantity]],"check data") -> 47840 | W3: =PROPER(TRIM(Table1[[#This Row],[Customer_Name]])) -> Asha Stores | X3: =UPPER(TRIM(Table1[[#This Row],[Region]])) -> NORTH | Y3: =TEXT(Table1[[#This Row],[Date]],"MMMM-yyyy") -> January-2026 | Z3: =MID(Table1[[#This Row],[Transaction_ID]],4,6) -> 1001 | AA3: =Table1[[#This Row],[Region]]&"-"&Table1[[#This Row],[Category]] -> North-Electronics
A4: TXN1036 | B4: 46091 | C4: East | D4: Wholesale | E4: Juniper Distributors | F4: Electronics | G4: Projector | H4: 2 | I4: 46500 | J4: 0.08 | K4: Bank Transfer | L4: Completed | M4: EMP04 | N4: =Table1[[#This Row],[Quantity]]*Table1[[#This Row],[Unit_Price_INR]] -> 93000 | O4: =Table1[[#This Row],[Grow Sales]]*Table1[[#This Row],[Discount_Rate]] -> 7440 | P4: =Table1[[#This Row],[Grow Sales]]-Table1[[#This Row],[Discount Amount]] -> 85560 | Q4: =TEXT(Table1[[#This Row],[Date]],"MMM-ddd-yyyy") -> Mar-Tue-2026 | R4: =IF(OR(Table1[[#This Row],[Status]]="Pending",Table1[[#This Row],[Status]]="Refunded"),"Review","OK") -> OK | S4: =IF(Table1[[#This Row],[Net Sales]]>=25000,"High",IF(Table1[[#This Row],[Net Sales]]>=10000,"Medium","Low")) -> High | T4: =IF(AND(Table1[[#This Row],[Quantity]]>=5,Table1[[#This Row],[Discount_Rate]]>=10%),"Review","OK") -> OK | U4: =IF(OR(Table1[[#This Row],[Payment_Method]]="Cash",Table1[[#This Row],[Payment_Method]]="UPI"),"YES","NO") -> NO | V4: =IFERROR(Table1[[#This Row],[Net Sales]]/Table1[[#This Row],[Quantity]],"check data") -> 42780 | W4: =PROPER(TRIM(Table1[[#This Row],[Customer_Name]])) -> Juniper Distributors | X4: =UPPER(TRIM(Table1[[#This Row],[Region]])) -> EAST | Y4: =TEXT(Table1[[#This Row],[Date]],"MMMM-yyyy") -> March-2026 | Z4: =MID(Table1[[#This Row],[Transaction_ID]],4,6) -> 1036 | AA4: =Table1[[#This Row],[Region]]&"-"&Table1[[#This Row],[Category]] -> East-Electronics
A5: TXN1045 | B5: 46110 | C5: North | D5: Wholesale | E5: Silverline Traders | F5: Electronics | G5: Camera | H5: 2 | I5: 42000 | J5: 0.07 | K5: Bank Transfer | L5: Completed | M5: EMP01 | N5: =Table1[[#This Row],[Quantity]]*Table1[[#This Row],[Unit_Price_INR]] -> 84000 | O5: =Table1[[#This Row],[Grow Sales]]*Table1[[#This Row],[Discount_Rate]] -> 5880 | P5: =Table1[[#This Row],[Grow Sales]]-Table1[[#This Row],[Discount Amount]] -> 78120 | Q5: =TEXT(Table1[[#This Row],[Date]],"MMM-ddd-yyyy") -> Mar-Sun-2026 | R5: =IF(OR(Table1[[#This Row],[Status]]="Pending",Table1[[#This Row],[Status]]="Refunded"),"Review","OK") -> OK | S5: =IF(Table1[[#This Row],[Net Sales]]>=25000,"High",IF(Table1[[#This Row],[Net Sales]]>=10000,"Medium","Low")) -> High | T5: =IF(AND(Table1[[#This Row],[Quantity]]>=5,Table1[[#This Row],[Discount_Rate]]>=10%),"Review","OK") -> OK | U5: =IF(OR(Table1[[#This Row],[Payment_Method]]="Cash",Table1[[#This Row],[Payment_Method]]="UPI"),"YES","NO") -> NO | V5: =IFERROR(Table1[[#This Row],[Net Sales]]/Table1[[#This Row],[Quantity]],"check data") -> 39060 | W5: =PROPER(TRIM(Table1[[#This Row],[Customer_Name]])) -> Silverline Traders | X5: =UPPER(TRIM(Table1[[#This Row],[Region]])) -> NORTH | Y5: =TEXT(Table1[[#This Row],[Date]],"MMMM-yyyy") -> March-2026 | Z5: =MID(Table1[[#This Row],[Transaction_ID]],4,6) -> 1045 | AA5: =Table1[[#This Row],[Region]]&"-"&Table1[[#This Row],[Category]] -> North-Electronics
A6: TXN1019 | B6: 46055 | C6: West | D6: Online | E6: Sunrise Shop | F6: Electronics | G6: Tablet | H6: 4 | I6: 22000 | J6: 0.12 | K6: Card | L6: Completed | M6: EMP02 | N6: =Table1[[#This Row],[Quantity]]*Table1[[#This Row],[Unit_Price_INR]] -> 88000 | O6: =Table1[[#This Row],[Grow Sales]]*Table1[[#This Row],[Discount_Rate]] -> 10560 | P6: =Table1[[#This Row],[Grow Sales]]-Table1[[#This Row],[Discount Amount]] -> 77440 | Q6: =TEXT(Table1[[#This Row],[Date]],"MMM-ddd-yyyy") -> Feb-Mon-2026 | R6: =IF(OR(Table1[[#This Row],[Status]]="Pending",Table1[[#This Row],[Status]]="Refunded"),"Review","OK") -> OK | S6: =IF(Table1[[#This Row],[Net Sales]]>=25000,"High",IF(Table1[[#This Row],[Net Sales]]>=10000,"Medium","Low")) -> High | T6: =IF(AND(Table1[[#This Row],[Quantity]]>=5,Table1[[#This Row],[Discount_Rate]]>=10%),"Review","OK") -> OK | U6: =IF(OR(Table1[[#This Row],[Payment_Method]]="Cash",Table1[[#This Row],[Payment_Method]]="UPI"),"YES","NO") -> NO | V6: =IFERROR(Table1[[#This Row],[Net Sales]]/Table1[[#This Row],[Quantity]],"check data") -> 19360 | W6: =PROPER(TRIM(Table1[[#This Row],[Customer_Name]])) -> Sunrise Shop | X6: =UPPER(TRIM(Table1[[#This Row],[Region]])) -> WEST | Y6: =TEXT(Table1[[#This Row],[Date]],"MMMM-yyyy") -> February-2026 | Z6: =MID(Table1[[#This Row],[Transaction_ID]],4,6) -> 1019 | AA6: =Table1[[#This Row],[Region]]&"-"&Table1[[#This Row],[Category]] -> West-Electronics
A7: TXN1006 | B7: 46031 | C7: South | D7: Retail | E7: Fresh Basket | F7: Grocery | G7: Cooking Oil | H7: 12 | I7: 185 | J7: 0.03 | K7: UPI | L7: Completed | M7: EMP05 | N7: =Table1[[#This Row],[Quantity]]*Table1[[#This Row],[Unit_Price_INR]] -> 2220 | O7: =Table1[[#This Row],[Grow Sales]]*Table1[[#This Row],[Discount_Rate]] -> 66.6 | P7: =Table1[[#This Row],[Grow Sales]]-Table1[[#This Row],[Discount Amount]] -> 2153.4 | Q7: =TEXT(Table1[[#This Row],[Date]],"MMM-ddd-yyyy") -> Jan-Fri-2026 | R7: =IF(OR(Table1[[#This Row],[Status]]="Pending",Table1[[#This Row],[Status]]="Refunded"),"Review","OK") -> OK | S7: =IF(Table1[[#This Row],[Net Sales]]>=25000,"High",IF(Table1[[#This Row],[Net Sales]]>=10000,"Medium","Low")) -> Low | T7: =IF(AND(Table1[[#This Row],[Quantity]]>=5,Table1[[#This Row],[Discount_Rate]]>=10%),"Review","OK") -> OK | U7: =IF(OR(Table1[[#This Row],[Payment_Method]]="Cash",Table1[[#This Row],[Payment_Method]]="UPI"),"YES","NO") -> YES | V7: =IFERROR(Table1[[#This Row],[Net Sales]]/Table1[[#This Row],[Quantity]],"check data") -> 179.45 | W7: =PROPER(TRIM(Table1[[#This Row],[Customer_Name]])) -> Fresh Basket | X7: =UPPER(TRIM(Table1[[#This Row],[Region]])) -> SOUTH | Y7: =TEXT(Table1[[#This Row],[Date]],"MMMM-yyyy") -> January-2026 | Z7: =MID(Table1[[#This Row],[Transaction_ID]],4,6) -> 1006 | AA7: =Table1[[#This Row],[Region]]&"-"&Table1[[#This Row],[Category]] -> South-Grocery
A8: TXN1007 | B8: 46032 | C8: West | D8: Online | E8: Global Needs | F8: Electronics | G8: Headphones | H8: 8 | I8: 1800 | J8: 0.12 | K8: Card | L8: Pending | M8: EMP02 | N8: =Table1[[#This Row],[Quantity]]*Table1[[#This Row],[Unit_Price_INR]] -> 14400 | O8: =Table1[[#This Row],[Grow Sales]]*Table1[[#This Row],[Discount_Rate]] -> 1728 | P8: =Table1[[#This Row],[Grow Sales]]-Table1[[#This Row],[Discount Amount]] -> 12672 | Q8: =TEXT(Table1[[#This Row],[Date]],"MMM-ddd-yyyy") -> Jan-Sat-2026 | R8: =IF(OR(Table1[[#This Row],[Status]]="Pending",Table1[[#This Row],[Status]]="Refunded"),"Review","OK") -> Review | S8: =IF(Table1[[#This Row],[Net Sales]]>=25000,"High",IF(Table1[[#This Row],[Net Sales]]>=10000,"Medium","Low")) -> Medium | T8: =IF(AND(Table1[[#This Row],[Quantity]]>=5,Table1[[#This Row],[Discount_Rate]]>=10%),"Review","OK") -> Review | U8: =IF(OR(Table1[[#This Row],[Payment_Method]]="Cash",Table1[[#This Row],[Payment_Method]]="UPI"),"YES","NO") -> NO | V8: =IFERROR(Table1[[#This Row],[Net Sales]]/Table1[[#This Row],[Quantity]],"check data") -> 1584 | W8: =PROPER(TRIM(Table1[[#This Row],[Customer_Name]])) -> Global Needs | X8: =UPPER(TRIM(Table1[[#This Row],[Region]])) -> WEST | Y8: =TEXT(Table1[[#This Row],[Date]],"MMMM-yyyy") -> January-2026 | Z8: =MID(Table1[[#This Row],[Transaction_ID]],4,6) -> 1007 | AA8: =Table1[[#This Row],[Region]]&"-"&Table1[[#This Row],[Category]] -> West-Electronics
A9: TXN1033 | B9: 46085 | C9: North | D9: Wholesale | E9: Grove Traders | F9: Home | G9: Refrigerator | H9: 2 | I9: 38500 | J9: 0.06 | K9: Bank Transfer | L9: Completed | M9: EMP01 | N9: =Table1[[#This Row],[Quantity]]*Table1[[#This Row],[Unit_Price_INR]] -> 77000 | O9: =Table1[[#This Row],[Grow Sales]]*Table1[[#This Row],[Discount_Rate]] -> 4620 | P9: =Table1[[#This Row],[Grow Sales]]-Table1[[#This Row],[Discount Amount]] -> 72380 | Q9: =TEXT(Table1[[#This Row],[Date]],"MMM-ddd-yyyy") -> Mar-Wed-2026 | R9: =IF(OR(Table1[[#This Row],[Status]]="Pending",Table1[[#This Row],[Status]]="Refunded"),"Review","OK") -> OK | S9: =IF(Table1[[#This Row],[Net Sales]]>=25000,"High",IF(Table1[[#This Row],[Net Sales]]>=10000,"Medium","Low")) -> High | T9: =IF(AND(Table1[[#This Row],[Quantity]]>=5,Table1[[#This Row],[Discount_Rate]]>=10%),"Review","OK") -> OK | U9: =IF(OR(Table1[[#This Row],[Payment_Method]]="Cash",Table1[[#This Row],[Payment_Method]]="UPI"),"YES","NO") -> NO | V9: =IFERROR(Table1[[#This Row],[Net Sales]]/Table1[[#This Row],[Quantity]],"check data") -> 36190 | W9: =PROPER(TRIM(Table1[[#This Row],[Customer_Name]])) -> Grove Traders | X9: =UPPER(TRIM(Table1[[#This Row],[Region]])) -> NORTH | Y9: =TEXT(Table1[[#This Row],[Date]],"MMMM-yyyy") -> March-2026 | Z9: =MID(Table1[[#This Row],[Transaction_ID]],4,6) -> 1033 | AA9: =Table1[[#This Row],[Region]]&"-"&Table1[[#This Row],[Category]] -> North-Home
A10: TXN1004 | B10: 46028 | C10: East | D10: Wholesale | E10: Delta Traders | F10: Office | G10: Printer | H10: 4 | I10: 18500 | J10: 0.1 | K10: Bank Transfer | L10: Completed | M10: EMP04 | N10: =Table1[[#This Row],[Quantity]]*Table1[[#This Row],[Unit_Price_INR]] -> 74000 | O10: =Table1[[#This Row],[Grow Sales]]*Table1[[#This Row],[Discount_Rate]] -> 7400 | P10: =Table1[[#This Row],[Grow Sales]]-Table1[[#This Row],[Discount Amount]] -> 66600 | Q10: =TEXT(Table1[[#This Row],[Date]],"MMM-ddd-yyyy") -> Jan-Tue-2026 | R10: =IF(OR(Table1[[#This Row],[Status]]="Pending",Table1[[#This Row],[Status]]="Refunded"),"Review","OK") -> OK | S10: =IF(Table1[[#This Row],[Net Sales]]>=25000,"High",IF(Table1[[#This Row],[Net Sales]]>=10000,"Medium","Low")) -> High | T10: =IF(AND(Table1[[#This Row],[Quantity]]>=5,Table1[[#This Row],[Discount_Rate]]>=10%),"Review","OK") -> OK | U10: =IF(OR(Table1[[#This Row],[Payment_Method]]="Cash",Table1[[#This Row],[Payment_Method]]="UPI"),"YES","NO") -> NO | V10: =IFERROR(Table1[[#This Row],[Net Sales]]/Table1[[#This Row],[Quantity]],"check data") -> 16650 | W10: =PROPER(TRIM(Table1[[#This Row],[Customer_Name]])) -> Delta Traders | X10: =UPPER(TRIM(Table1[[#This Row],[Region]])) -> EAST | Y10: =TEXT(Table1[[#This Row],[Date]],"MMMM-yyyy") -> January-2026 | Z10: =MID(Table1[[#This Row],[Transaction_ID]],4,6) -> 1004 | AA10: =Table1[[#This Row],[Region]]&"-"&Table1[[#This Row],[Category]] -> East-Office
A11: TXN1010 | B11: 46036 | C11: South | D11: Online | E11: Jasmine Market | F11: Fashion | G11: Shoes | H11: 6 | I11: 3200 | J11: 0.2 | K11: UPI | L11: Refunded | M11: EMP05 | N11: =Table1[[#This Row],[Quantity]]*Table1[[#This Row],[Unit_Price_INR]] -> 19200 | O11: =Table1[[#This Row],[Grow Sales]]*Table1[[#This Row],[Discount_Rate]] -> 3840 | P11: =Table1[[#This Row],[Grow Sales]]-Table1[[#This Row],[Discount Amount]] -> 15360 | Q11: =TEXT(Table1[[#This Row],[Date]],"MMM-ddd-yyyy") -> Jan-Wed-2026 | R11: =IF(OR(Table1[[#This Row],[Status]]="Pending",Table1[[#This Row],[Status]]="Refunded"),"Review","OK") -> Review | S11: =IF(Table1[[#This Row],[Net Sales]]>=25000,"High",IF(Table1[[#This Row],[Net Sales]]>=10000,"Medium","Low")) -> Medium | T11: =IF(AND(Table1[[#This Row],[Quantity]]>=5,Table1[[#This Row],[Discount_Rate]]>=10%),"Review","OK") -> Review | U11: =IF(OR(Table1[[#This Row],[Payment_Method]]="Cash",Table1[[#This Row],[Payment_Method]]="UPI"),"YES","NO") -> YES | V11: =IFERROR(Table1[[#This Row],[Net Sales]]/Table1[[#This Row],[Quantity]],"check data") -> 2560 | W11: =PROPER(TRIM(Table1[[#This Row],[Customer_Name]])) -> Jasmine Market | X11: =UPPER(TRIM(Table1[[#This Row],[Region]])) -> SOUTH | Y11: =TEXT(Table1[[#This Row],[Date]],"MMMM-yyyy") -> January-2026 | Z11: =MID(Table1[[#This Row],[Transaction_ID]],4,6) -> 1010 | AA11: =Table1[[#This Row],[Region]]&"-"&Table1[[#This Row],[Category]] -> South-Fashion
A12: TXN1048 | B12: 46118 | C12: East | D12: Wholesale | E12: Vista Traders | F12: Home | G12: Washing Machine | H12: 2 | I12: 31500 | J12: 0.08 | K12: Bank Transfer | L12: Completed | M12: EMP04 | N12: =Table1[[#This Row],[Quantity]]*Table1[[#This Row],[Unit_Price_INR]] -> 63000 | O12: =Table1[[#This Row],[Grow Sales]]*Table1[[#This Row],[Discount_Rate]] -> 5040 | P12: =Table1[[#This Row],[Grow Sales]]-Table1[[#This Row],[Discount Amount]] -> 57960 | Q12: =TEXT(Table1[[#This Row],[Date]],"MMM-ddd-yyyy") -> Apr-Mon-2026 | R12: =IF(OR(Table1[[#This Row],[Status]]="Pending",Table1[[#This Row],[Status]]="Refunded"),"Review","OK") -> OK | S12: =IF(Table1[[#This Row],[Net Sales]]>=25000,"High",IF(Table1[[#This Row],[Net Sales]]>=10000,"Medium","Low")) -> High | T12: =IF(AND(Table1[[#This Row],[Quantity]]>=5,Table1[[#This Row],[Discount_Rate]]>=10%),"Review","OK") -> OK | U12: =IF(OR(Table1[[#This Row],[Payment_Method]]="Cash",Table1[[#This Row],[Payment_Method]]="UPI"),"YES","NO") -> NO | V12: =IFERROR(Table1[[#This Row],[Net Sales]]/Table1[[#This Row],[Quantity]],"check data") -> 28980 | W12: =PROPER(TRIM(Table1[[#This Row],[Customer_Name]])) -> Vista Traders | X12: =UPPER(TRIM(Table1[[#This Row],[Region]])) -> EAST | Y12: =TEXT(Table1[[#This Row],[Date]],"MMMM-yyyy") -> April-2026 | Z12: =MID(Table1[[#This Row],[Transaction_ID]],4,6) -> 1048 | AA12: =Table1[[#This Row],[Region]]&"-"&Table1[[#This Row],[Category]] -> East-Home
A13: TXN1011 | B13: 46037 | C13: West | D13: Retail | E13: Kingfisher Store | F13: Electronics | G13: Monitor | H13: 4 | I13: 11200 | J13: 0.08 | K13: Card | L13: Completed | M13: EMP02 | N13: =Table1[[#This Row],[Quantity]]*Table1[[#This Row],[Unit_Price_INR]] -> 44800 | O13: =Table1[[#This Row],[Grow Sales]]*Table1[[#This Row],[Discount_Rate]] -> 3584 | P13: =Table1[[#This Row],[Grow Sales]]-Table1[[#This Row],[Discount Amount]] -> 41216 | Q13: =TEXT(Table1[[#This Row],[Date]],"MMM-ddd-yyyy") -> Jan-Thu-2026 | R13: =IF(OR(Table1[[#This Row],[Status]]="Pending",Table1[[#This Row],[Status]]="Refunded"),"Review","OK") -> OK | S13: =IF(Table1[[#This Row],[Net Sales]]>=25000,"High",IF(Table1[[#This Row],[Net Sales]]>=10000,"Medium","Low")) -> High | T13: =IF(AND(Table1[[#This Row],[Quantity]]>=5,Table1[[#This Row],[Discount_Rate]]>=10%),"Review","OK") -> OK | U13: =IF(OR(Table1[[#This Row],[Payment_Method]]="Cash",Table1[[#This Row],[Payment_Method]]="UPI"),"YES","NO") -> NO | V13: =IFERROR(Table1[[#This Row],[Net Sales]]/Table1[[#This Row],[Quantity]],"check data") -> 10304 | W13: =PROPER(TRIM(Table1[[#This Row],[Customer_Name]])) -> Kingfisher Store | X13: =UPPER(TRIM(Table1[[#This Row],[Region]])) -> WEST | Y13: =TEXT(Table1[[#This Row],[Date]],"MMMM-yyyy") -> January-2026 | Z13: =MID(Table1[[#This Row],[Transaction_ID]],4,6) -> 1011 | AA13: =Table1[[#This Row],[Region]]&"-"&Table1[[#This Row],[Category]] -> West-Electronics
... A77: TXN1077 | B77: 46172 | C77: East | D77: Wholesale | E77: Xylem Traders | F77: Home | G77: Storage Rack | H77: 2 | I77: 4800 | J77: 0.06 | K77: Bank Transfer | L77: Completed | M77: EMP04 | N77: =Table1[[#This Row],[Quantity]]*Table1[[#This Row],[Unit_Price_INR]] -> 9600 | O77: =Table1[[#This Row],[Grow Sales]]*Table1[[#This Row],[Discount_Rate]] -> 576 | P77: =Table1[[#This Row],[Grow Sales]]-Table1[[#This Row],[Discount Amount]] -> 9024 | Q77: =TEXT(Table1[[#This Row],[Date]],"MMM-ddd-yyyy") -> May-Sat-2026 | R77: =IF(OR(Table1[[#This Row],[Status]]="Pending",Table1[[#This Row],[Status]]="Refunded"),"Review","OK") -> OK | S77: =IF(Table1[[#This Row],[Net Sales]]>=25000,"High",IF(Table1[[#This Row],[Net Sales]]>=10000,"Medium","Low")) -> Low | T77: =IF(AND(Table1[[#This Row],[Quantity]]>=5,Table1[[#This Row],[Discount_Rate]]>=10%),"Review","OK") -> OK | U77: =IF(OR(Table1[[#This Row],[Payment_Method]]="Cash",Table1[[#This Row],[Payment_Method]]="UPI"),"YES","NO") -> NO | V77: =IFERROR(Table1[[#This Row],[Net Sales]]/Table1[[#This Row],[Quantity]],"check data") -> 4512 | W77: =PROPER(TRIM(Table1[[#This Row],[Customer_Name]])) -> Xylem Traders | X77: =UPPER(TRIM(Table1[[#This Row],[Region]])) -> EAST | Y77: =TEXT(Table1[[#This Row],[Date]],"MMMM-yyyy") -> May-2026 | Z77: =MID(Table1[[#This Row],[Transaction_ID]],4,6) -> 1077 | AA77: =Table1[[#This Row],[Region]]&"-"&Table1[[#This Row],[Category]] -> East-Home
G80: T05 | H80: avg.unitprice | I80: =AVERAGE(Table1[Unit_Price_INR]) -> 6655.7895 | T80: T11 | U80: sumif(nor) | V80: =SUMIF(Table1[Region],"North",Table1[Net Sales]) -> 499870.9
G82: T05 | H82: total quantity | I82: =SUM(Table1[Quantity]) -> 592 | T82: T12 | U82: sumifs(s,co) | V82: =SUMIFS(Table1[Net Sales],Table1[Region],"South",Table1[Status],"Completed") -> 128509.4
G84: T05 | H84: total netsales | I84: =SUM(Table1[Net Sales]) -> 1594263.8 | T84: T13 | U84: countif(pend) | V84: =COUNTIF(Table1[Status],"Pending") -> 5
H86: avgorder | I86: =SUM(P2:P74)/COUNTA(A2:A74) -> 21570.932 | T86: T14 | U86: countifs(o,e) | V86: =COUNTIFS(Table1[Payment_Method],"UPI",Table1[Category],"Electronics") -> 4
H88: total trans | I88: =COUNTA(L2:L74) -> 73 | T88: T15 | U88: averageif | V88: =AVERAGEIF(Table1[Category],"Home",Table1[Unit_Price_INR]) -> 9755.625

Sheet answers
A1: SECTION A-T05
A2: avg.unitprice | B2: =Sheet1!I80 -> 6655.7895
A3: total quantity | B3: =Sheet1!I82 -> 592
A4: total netsales | B4: =Sheet1!I84 -> 1594263.8
A6: SECTION C
A7: T11 | B7: =Sheet1!V80 -> 499870.9
A8: T12 | B8: =Sheet1!V82 -> 128509.4
A9: T13 | B9: =Sheet1!V84 -> 5
A10: T14 | B10: =Sheet1!V86 -> 4
A11: T15 | B11: =Sheet1!V88 -> 9755.625
A15: SECTION D
A17: T17 | B17: EMP02 | C17: =VLOOKUP(B17,lookuptable!A2:B6,2,FALSE) -> Keerthi
A18: T18 | B18: TXN1003 | C18: =INDEX(Sheet1!I2:I77,MATCH(answers!B18,Sheet1!A2:A77,0)) -> 1250
A19: T19 | B19: =MATCH("Smartphone",Sheet1!G2:G77,0) -> 1
A20: T20 | B20: T-shirt | C20: =_xlfn.XLOOKUP(B20,Sheet1!G2:G77,Sheet1!F2:F77) -> Fashion

Sheet lookuptable
A1: sales_id | B1: sales_rep
A2: EMP01 | B2: Miya
A3: EMP02 | B3: Keerthi
A4: EMP03 | B4: Sudha
A5: EMP04 | B5: Manu
A6: EMP05 | B6: Devi

Sheet original
A1: Transaction_ID | B1: Date | C1: Region | D1: Sales_Channel | E1: Customer_Name | F1: Category | G1: Product | H1: Quantity | I1: Unit_Price_INR | J1: Discount_Rate | K1: Payment_Method | L1: Status | M1: Sales_Rep_ID
A2: TXN1001 | B2: 46025 | C2: North | D2: Retail | E2: Asha Stores | F2: Electronics | G2: Laptop | H2: 2 | I2: 52000 | J2: 0.08 | K2: UPI | L2: Completed | M2: EMP01
A3: TXN1002 | B3: 46026 | C3: South | D3: Online | E3: Bright Mart | F3: Home | G3: Mixer Grinder | H3: 3 | I3: 4200 | J3: 0.05 | K3: Card | L3: Completed | M3: EMP03
A4: TXN1003 | B4: 46027 | C4: West | D4: Retail | E4: City Bazaar | F4: Grocery | G4: Rice Bag | H4: 10 | I4: 1250 | J4: 0 | K4: Cash | L4: Completed | M4: EMP02
A5: TXN1004 | B5: 46028 | C5: East | D5: Wholesale | E5: Delta Traders | F5: Office | G5: Printer | H5: 4 | I5: 18500 | J5: 0.1 | K5: Bank Transfer | L5: Completed | M5: EMP04
A6: TXN1005 | B6: 46029 | C6: North | D6: Online | E6: Evergreen Shop | F6: Fashion | G6: Jacket | H6: 5 | I6: 2400 | J6: 0.15 | K6: Card | L6: Completed | M6: EMP01
A7: TXN1006 | B7: 46031 | C7: South | D7: Retail | E7: Fresh Basket | F7: Grocery | G7: Cooking Oil | H7: 12 | I7: 185 | J7: 0.03 | K7: UPI | L7: Completed | M7: EMP05
A8: TXN1007 | B8: 46032 | C8: West | D8: Online | E8: Global Needs | F8: Electronics | G8: Headphones | H8: 8 | I8: 1800 | J8: 0.12 | K8: Card | L8: Pending | M8: EMP02
A9: TXN1008 | B9: 46033 | C9: East | D9: Retail | E9: Harbor Supplies | F9: Office | G9: Office Chair | H9: 3 | I9: 7800 | J9: 0.07 | K9: Bank Transfer | L9: Completed | M9: EMP04
A10: TXN1009 | B10: 46034 | C10: North | D10: Wholesale | E10: Indigo Retailers | F10: Home | G10: Water Purifier | H10: 2 | I10: 14500 | J10: 0.05 | K10: Bank Transfer | L10: Completed | M10: EMP03
A11: TXN1010 | B11: 46036 | C11: South | D11: Online | E11: Jasmine Market | F11: Fashion | G11: Shoes | H11: 6 | I11: 3200 | J11: 0.2 | K11: UPI | L11: Refunded | M11: EMP05
A12: TXN1011 | B12: 46037 | C12: West | D12: Retail | E12: Kingfisher Store | F12: Electronics | G12: Monitor | H12: 4 | I12: 11200 | J12: 0.08 | K12: Card | L12: Completed | M12: EMP02
A13: TXN1012 | B13: 46039 | C13: East | D13: Wholesale | E13: Lotus Distributors | F13: Grocery | G13: Wheat Flour | H13: 20 | I13: 650 | J13: 0.02 | K13: Bank Transfer | L13: Completed | M13: EMP04
... A78: TXN1077 | B78: 46172 | C78: East | D78: Wholesale | E78: Xylem Traders | F78: Home | G78: Storage Rack | H78: 2 | I78: 4800 | J78: 0.06 | K78: Bank Transfer | L78: Completed | M78: EMP04
